Cycle 1/Experiment 4/4.v
module Mux4to1(t1, t2, t3, t4, sel1, sel2, op);
    input t1, t2, t3, t4, sel1, sel2;
    output op;
    wire a, b, c, d;

    and a1(a, t1, ~sel1, ~sel2);
    and a2(b, t2, ~sel1, sel2);
    and a3(c, t3, sel1, ~sel2);
    and a4(d, t4, sel1, sel2);
    or o1(op, a, b, c, d);
endmodule

module test;
    reg t1, t2, t3, t4, sel1, sel2;
    wire op;
    Mux4to1 muxg(t1, t2, t3, t4, sel1, sel2, op);

    initial begin
        $dumpfile("4.vcd");
        $dumpvars(0, test);
        t1 = 0; t2 = 0; t3 = 0; t4 = 0; sel1 = 0; sel2 = 0; #20;
        t1 = 1; t2 = 0; t3 = 0; t4 = 0; sel1 = 0; sel2 = 0; #20;
        t1 = 0; t2 = 0; t3 = 0; t4 = 0; sel1 = 0; sel2 = 1; #20;
        t1 = 1; t2 = 1; t3 = 0; t4 = 0; sel1 = 0; sel2 = 1; #20;
        t1 = 0; t2 = 0; t3 = 1; t4 = 0; sel1 = 1; sel2 = 0; #20;
        t1 = 1; t2 = 1; t3 = 0; t4 = 1; sel1 = 1; sel2 = 0; #20;
        t1 = 1; t2 = 0; t3 = 0; t4 = 1; sel1 = 1; sel2 = 1; #20;
        t1 = 0; t2 = 1; t3 = 1; t4 = 0; sel1 = 1; sel2 = 1; #20;
        $finish;
    end
endmodule

Cycle 1/Experiment 4/4.vcd
$date
	Mon Dec 30 02:06:27 2024
$end
$version
	Icarus Verilog
$end
$timescale
	1s
$end
$scope module test $end
$var wire 1 ! op $end
$var reg 1 " sel1 $end
$var reg 1 # sel2 $end
$var reg 1 $ t1 $end
$var reg 1 % t2 $end
$var reg 1 & t3 $end
$var reg 1 ' t4 $end
$scope module muxg $end
$var wire 1 ( a $end
$var wire 1 ) b $end
$var wire 1 * c $end
$var wire 1 + d $end
$var wire 1 ! op $end
$var wire 1 " sel1 $end
$var wire 1 # sel2 $end
$var wire 1 $ t1 $end
$var wire 1 % t2 $end
$var wire 1 & t3 $end
$var wire 1 ' t4 $end
$upscope $end
$upscope $end
$enddefinitions $end
$comment Show the parameter values. $end
$dumpall
$end
#0
$dumpvars
0+
0*
0)
0(
0'
0&
0%
0$
0#
0"
0!
$end
#20
1!
1(
1$
#40
0!
0(
1#
0$
#60
1!
1)
1%
1$
#80
1*
1!
0)
0#
1"
1&
0%
0$
#100
0!
0*
1'
0&
1%
1$
#120
1!
1+
1#
0%
#140
0!
0+
0'
1&
1%
0$
