Cycle 2/Experiment 9/9.v
module counter_behav(count, rst, clk);
    input rst, clk;
    output reg [2:0] count;

    always @(posedge clk) begin
        if (rst)
            count <= 3'b000;
        else
            count <= count + 1;
    end
endmodule

module test_mod;
    reg rst, clk;
    wire [2:0] count;
    
    counter_behav countbeh(count, rst, clk);
    
    initial begin
        $dumpfile("9.vcd");
        $dumpvars(0, test_mod);
        
        rst = 1;
        clk = 0;
        #100;
        
        rst = 0;
        #200;
        
        $finish;
    end
    
    always #5 clk = ~clk;
endmodule

Cycle 2/Experiment 9/9.vcd
$date
	Mon Dec 30 02:16:53 2024
$end
$version
	Icarus Verilog
$end
$timescale
	1s
$end
$scope module test_mod $end
$var wire 3 ! count [2:0] $end
$var reg 1 " clk $end
$var reg 1 # rst $end
$scope module countbeh $end
$var wire 1 " clk $end
$var wire 1 # rst $end
$var reg 3 $ count [2:0] $end
$upscope $end
$upscope $end
$enddefinitions $end
$comment Show the parameter values. $end
$dumpall
$end
#0
$dumpvars
bx $
1#
0"
bx !
$end
#5
b0 !
b0 $
1"
#10
0"
#15
1"
#20
0"
#25
1"
#30
0"
#35
1"
#40
0"
#45
1"
#50
0"
#55
1"
#60
0"
#65
1"
#70
0"
#75
1"
#80
0"
#85
1"
#90
0"
#95
1"
#100
0"
0#
#105
b1 !
b1 $
1"
#110
0"
#115
b10 !
b10 $
1"
#120
0"
#125
b11 !
b11 $
1"
#130
0"
#135
b100 !
b100 $
1"
#140
0"
#145
b101 !
b101 $
1"
#150
0"
#155
b110 !
b110 $
1"
#160
0"
#165
b111 !
b111 $
1"
#170
0"
#175
b0 !
b0 $
1"
#180
0"
#185
b1 !
b1 $
1"
#190
0"
#195
b10 !
b10 $
1"
#200
0"
#205
b11 !
b11 $
1"
#210
0"
#215
b100 !
b100 $
1"
#220
0"
#225
b101 !
b101 $
1"
#230
0"
#235
b110 !
b110 $
1"
#240
0"
#245
b111 !
b111 $
1"
#250
0"
#255
b0 !
b0 $
1"
#260
0"
#265
b1 !
b1 $
1"
#270
0"
#275
b10 !
b10 $
1"
#280
0"
#285
b11 !
b11 $
1"
#290
0"
#295
b100 !
b100 $
1"
